kawaiiapi/__init__.py
kawaiiapi/kawaiiapi.py
kawaiiapi/stats.py
kawaiiapi-1.2.5.dist-info/LICENSE.txt
kawaiiapi-1.2.5.dist-info/METADATA
kawaiiapi-1.2.5.dist-info/WHEEL
kawaiiapi-1.2.5.dist-info/top_level.txt
kawaiiapi-1.2.5.dist-info/RECORD
