Metadata-Version: 2.1
Name: kawaiiapi
Version: 1.2.5
Summary: The kawaii api from Error44 as python package
Home-page: https://github.com/keksiqc/kawaiiapi-py
Author: Keksiqc
Author-email: contact@keksi.me
License: MIT
Platform: UNKNOWN
Classifier: Programming Language :: Python :: 3
Classifier: License :: OSI Approved :: MIT License
Classifier: Operating System :: OS Independent
License-File: LICENSE.txt
Requires-Dist: aiohttp (>=3.6)
